brickmason/databricks/__init__.py
brick_mason_databricks-0.1.0.dist-info/METADATA
brick_mason_databricks-0.1.0.dist-info/WHEEL
brick_mason_databricks-0.1.0.dist-info/RECORD
