Metadata-Version: 2.3
Name: brick-mason-databricks
Version: 0.1.0
Summary: Core functionality for the brick-mason API.
Author: Rusty Swayne
Requires-Python: >=3.10,<4.0
Classifier: Programming Language :: Python :: 3
Classifier: Programming Language :: Python :: 3.10
Classifier: Programming Language :: Python :: 3.11
Classifier: Programming Language :: Python :: 3.12
Classifier: Programming Language :: Python :: 3.13
Requires-Dist: brick-mason-core (>=0.1.0,<0.2.0)
Requires-Dist: pyyaml (>=6.0.2,<7.0.0)
